{
  "config": {
    "title": "Prism Ui Docs",
    "description": "My awesome app using docz",
    "menu": [],
    "version": "0.0.1",
    "repository": null,
    "native": false,
    "themeConfig": {},
    "separator": "-",
    "typescript": true,
    "docgenConfig": {}
  },
  "entries": [
    {
      "key": "index.mdx",
      "value": {
        "name": "Getting Started",
        "route": "/",
        "id": "91149a4106ab27ef746308b41227aca8",
        "filepath": "index.mdx",
        "fullpath": "/Users/tyler.haas/Projects/octanner/prism-ui/packages/docs/index.mdx",
        "link": "",
        "slug": "index",
        "menu": "",
        "headings": [
          {
            "slug": "getting-started",
            "depth": 2,
            "value": "Getting Started"
          }
        ]
      }
    },
    {
      "key": "components/thing.mdx",
      "value": {
        "name": "Thing",
        "menu": "Components",
        "route": "/components/thing",
        "id": "638398abe7831b77c217b4820adf785e",
        "filepath": "components/thing.mdx",
        "fullpath": "/Users/tyler.haas/Projects/octanner/prism-ui/packages/docs/components/thing.mdx",
        "link": "",
        "slug": "components-thing",
        "headings": [
          {
            "slug": "thing",
            "depth": 1,
            "value": "Thing"
          },
          {
            "slug": "thing-props",
            "depth": 2,
            "value": "Thing Props"
          },
          {
            "slug": "basic-usage",
            "depth": 2,
            "value": "Basic Usage"
          }
        ]
      }
    }
  ],
  "props": []
}
